DevilNinja/__init__.py
DevilCore-2.dist-info/METADATA
DevilCore-2.dist-info/WHEEL
DevilCore-2.dist-info/top_level.txt
DevilCore-2.dist-info/RECORD
