Metadata-Version: 2.1
Name: DevilCore
Version: 2
Summary: Hello Devil
Author: DevilCore
Classifier: Programming Language :: Python :: 3
